jolt/__init__.py
jolt/__main__.py
jolt/cache.py
jolt/chroot.py
jolt/cli.py
jolt/colors.py
jolt/common_pb2.py
jolt/common_pb2_grpc.py
jolt/config.py
jolt/error.py
jolt/expires.py
jolt/filesystem.py
jolt/graph.py
jolt/hooks.py
jolt/influence.py
jolt/inspection.py
jolt/loader.py
jolt/log.py
jolt/manifest.py
jolt/options.py
jolt/scheduler.py
jolt/tasks.py
jolt/timer.py
jolt/tools.py
jolt/utils.py
jolt/version.py
jolt/version_utils.py
jolt/xmldom.py
jolt/bin/fstree-darwin-x86_64
jolt/bin/fstree-linux-x86_64
jolt/pkgs/__init__.py
jolt/pkgs/abseil.py
jolt/pkgs/asio.py
jolt/pkgs/autoconf.py
jolt/pkgs/automake.py
jolt/pkgs/b2.py
jolt/pkgs/blake3.py
jolt/pkgs/boost.py
jolt/pkgs/boringssl.py
jolt/pkgs/brotli.py
jolt/pkgs/busybox.py
jolt/pkgs/bzip2.py
jolt/pkgs/cares.py
jolt/pkgs/catch2.py
jolt/pkgs/cbindgen.py
jolt/pkgs/cista.py
jolt/pkgs/clang.py
jolt/pkgs/cli11.py
jolt/pkgs/cmake.py
jolt/pkgs/cpython.py
jolt/pkgs/crun.py
jolt/pkgs/curl.py
jolt/pkgs/dbus.py
jolt/pkgs/double_conversion.py
jolt/pkgs/fastfloat.py
jolt/pkgs/ffmpeg.py
jolt/pkgs/flatbuffers.py
jolt/pkgs/fmt.py
jolt/pkgs/fstree.py
jolt/pkgs/gflags.py
jolt/pkgs/glib.py
jolt/pkgs/glog.py
jolt/pkgs/glslang.py
jolt/pkgs/golang.py
jolt/pkgs/googlebenchmark.py
jolt/pkgs/googletest.py
jolt/pkgs/gperf.py
jolt/pkgs/grpc.py
jolt/pkgs/hdf5.py
jolt/pkgs/help2man.py
jolt/pkgs/inja.py
jolt/pkgs/jsoncpp.py
jolt/pkgs/libarchive.py
jolt/pkgs/libcap.py
jolt/pkgs/libdrm.py
jolt/pkgs/libedit.py
jolt/pkgs/libevent.py
jolt/pkgs/libexpat.py
jolt/pkgs/libfastjson.py
jolt/pkgs/libffi.py
jolt/pkgs/libglvnd.py
jolt/pkgs/libogg.py
jolt/pkgs/libpciaccess.py
jolt/pkgs/libseccomp.py
jolt/pkgs/libtirpc.py
jolt/pkgs/libtool.py
jolt/pkgs/libunwind.py
jolt/pkgs/libva.py
jolt/pkgs/libvorbis.py
jolt/pkgs/libxml2.py
jolt/pkgs/libxslt.py
jolt/pkgs/libyajl.py
jolt/pkgs/llvm.py
jolt/pkgs/lua.py
jolt/pkgs/lz4.py
jolt/pkgs/m4.py
jolt/pkgs/make.py
jolt/pkgs/mesa.py
jolt/pkgs/meson.py
jolt/pkgs/mstch.py
jolt/pkgs/mysql.py
jolt/pkgs/nasm.py
jolt-0.9.452.dist-info/METADATA
jolt-0.9.452.dist-info/WHEEL
jolt-0.9.452.dist-info/entry_points.txt
jolt-0.9.452.dist-info/top_level.txt
jolt-0.9.452.dist-info/RECORD
