Metadata-Version: 2.4
Name: jolt
Version: 0.9.452
Summary: A task executor
Home-page: https://github.com/srand/jolt
Author: Robert Andersson
Author-email: srand@github.com
Keywords: bazel,build,cmake,conan,jolt,make,meson,msbuild,xcode
Classifier: Development Status :: 5 - Production/Stable
Classifier: Intended Audience :: Developers
Classifier: Intended Audience :: System Administrators
Classifier: Topic :: Software Development :: Build Tools
Classifier: Topic :: Software Development :: Testing
Classifier: License :: OSI Approved :: GNU General Public License v2 (GPLv2)
Classifier: Operating System :: MacOS :: MacOS X
Classifier: Operating System :: Microsoft :: Windows
Classifier: Operating System :: POSIX
Classifier: Programming Language :: C
Classifier: Programming Language :: C++
Classifier: Programming Language :: Java
Classifier: Programming Language :: JavaScript
Classifier: Programming Language :: Python :: 3
Requires-Python: >=3.8
Requires-Dist: Jinja2==3.1.4
Requires-Dist: Jinja2==3.1.4
Requires-Dist: MarkupSafe==2.1.5
Requires-Dist: PyJWT==2.9.0
Requires-Dist: PyYAML==6.0.2
Requires-Dist: PyYAML==6.0.2
Requires-Dist: Pygments==2.18.0
Requires-Dist: Pygments==2.18.0
Requires-Dist: SecretStorage==3.3.3
Requires-Dist: allure-python-commons==2.13.5
Requires-Dist: attrs==24.2.0
Requires-Dist: backports.tarfile==1.2.0
Requires-Dist: blake3==1.0.8
Requires-Dist: bottle==0.12.25
Requires-Dist: brotli==1.2.0
Requires-Dist: bz2file==0.98
Requires-Dist: certifi==2024.8.30
Requires-Dist: cffi==1.17.1
Requires-Dist: charset-normalizer==3.3.2
Requires-Dist: click==8.1.7
Requires-Dist: colorama==0.4.6
Requires-Dist: conan==2.10.2
Requires-Dist: cryptography==43.0.1
Requires-Dist: distro==1.8.0
Requires-Dist: docutils==0.21.2
Requires-Dist: fasteners==0.19
Requires-Dist: flake8==7.1.1
Requires-Dist: grpcio==1.66.1
Requires-Dist: id==1.5.0
Requires-Dist: idna==3.10
Requires-Dist: importlib_metadata==8.5.0
Requires-Dist: importlib_metadata==8.5.0
Requires-Dist: inflate64==1.0.4
Requires-Dist: jaraco.classes==3.4.0
Requires-Dist: jaraco.context==6.0.1
Requires-Dist: jaraco.functools==4.0.2
Requires-Dist: jeepney==0.8.0
Requires-Dist: keyring==25.4.1
Requires-Dist: keyrings.alt==5.0.2
Requires-Dist: lxml==5.3.0
Requires-Dist: markdown-it-py==3.0.0
Requires-Dist: mccabe==0.7.0
Requires-Dist: more-itertools==10.5.0
Requires-Dist: more-itertools==10.5.0
Requires-Dist: multi_key_dict==2.0.3
Requires-Dist: multivolumefile==0.2.3
Requires-Dist: nh3==0.2.19
Requires-Dist: ninja==1.11.1.1
Requires-Dist: packaging==24.2
Requires-Dist: patch-ng==1.18.1
Requires-Dist: pip==25.3
Requires-Dist: pluggy==1.5.0
Requires-Dist: pluginbase==1.0.1
Requires-Dist: protobuf==5.28.2
Requires-Dist: psutil==6.0.0
Requires-Dist: py7zr==1.0.0
Requires-Dist: pybcj==1.0.6
Requires-Dist: pycodestyle==2.12.1
Requires-Dist: pycparser==2.22
Requires-Dist: pycryptodomex==3.23.0
Requires-Dist: pyflakes==3.2.0
Requires-Dist: pygit2==1.15.1
Requires-Dist: pyppmd==1.2.0
Requires-Dist: python-dateutil==2.9.0.post0
Requires-Dist: pyzstd==0.18.0
Requires-Dist: readme_renderer==44.0
Requires-Dist: requests-toolbelt==1.0.0
Requires-Dist: requests==2.32.3
Requires-Dist: rfc3986==2.0.0
Requires-Dist: rich==13.9.4
Requires-Dist: setuptools==80.9.0
Requires-Dist: six==1.16.0
Requires-Dist: texttable==1.7.0
Requires-Dist: tqdm==4.66.5
Requires-Dist: twine==6.2.0
Requires-Dist: typing_extensions==4.15.0
Requires-Dist: urllib3==1.26.20
Requires-Dist: wheel==0.46.3
Requires-Dist: zipp==3.20.2
Requires-Dist: zstandard==0.23.0
Provides-Extra: allure
Requires-Dist: allure-python-commons; extra == "allure"
Provides-Extra: conan
Requires-Dist: conan>=2.0; extra == "conan"
Provides-Extra: dev
Requires-Dist: check-manifest; extra == "dev"
Provides-Extra: doc
Requires-Dist: sphinx-click; extra == "doc"
Requires-Dist: sphinx-rtd-theme; extra == "doc"
Provides-Extra: test
Requires-Dist: coverage; extra == "test"
Dynamic: author
Dynamic: author-email
Dynamic: classifier
Dynamic: description
Dynamic: home-page
Dynamic: keywords
Dynamic: provides-extra
Dynamic: requires-dist
Dynamic: requires-python
Dynamic: summary
